{"nodes": [{"id": "home_user_imobi_security_audit_script_sh", "label": "SECURITY_AUDIT_SCRIPT.sh", "file_type": "code", "source_file": "SECURITY_AUDIT_SCRIPT.sh", "source_location": "L1", "metadata": {"language": "bash", "kind": "file"}}, {"id": "home_user_imobi_security_audit_script_sh__entry", "label": "SECURITY_AUDIT_SCRIPT.sh script", "file_type": "code", "source_file": "SECURITY_AUDIT_SCRIPT.sh", "source_location": "L1", "metadata": {"language": "bash", "kind": "bash_entrypoint"}}, {"id": "imobi_security_audit_script_pass", "label": "pass()", "file_type": "code", "source_file": "SECURITY_AUDIT_SCRIPT.sh", "source_location": "L33", "metadata": {"language": "bash", "kind": "bash_function"}}, {"id": "imobi_security_audit_script_fail", "label": "fail()", "file_type": "code", "source_file": "SECURITY_AUDIT_SCRIPT.sh", "source_location": "L38", "metadata": {"language": "bash", "kind": "bash_function"}}, {"id": "imobi_security_audit_script_warn", "label": "warn()", "file_type": "code", "source_file": "SECURITY_AUDIT_SCRIPT.sh", "source_location": "L43", "metadata": {"language": "bash", "kind": "bash_function"}}, {"id": "imobi_security_audit_script_check_env_var", "label": "check_env_var()", "file_type": "code", "source_file": "SECURITY_AUDIT_SCRIPT.sh", "source_location": "L52", "metadata": {"language": "bash", "kind": "bash_function"}}], "edges": [{"source": "home_user_imobi_security_audit_script_sh", "target": "home_user_imobi_security_audit_script_sh__entry", "relation": "contains", "confidence": "EXTRACTED", "source_file": "SECURITY_AUDIT_SCRIPT.sh", "source_location": "L1", "weight": 1.0}, {"source": "home_user_imobi_security_audit_script_sh", "target": "imobi_security_audit_script_pass", "relation": "defines", "confidence": "EXTRACTED", "source_file": "SECURITY_AUDIT_SCRIPT.sh", "source_location": "L33", "weight": 1.0}, {"source": "home_user_imobi_security_audit_script_sh", "target": "imobi_security_audit_script_fail", "relation": "defines", "confidence": "EXTRACTED", "source_file": "SECURITY_AUDIT_SCRIPT.sh", "source_location": "L38", "weight": 1.0}, {"source": "home_user_imobi_security_audit_script_sh", "target": "imobi_security_audit_script_warn", "relation": "defines", "confidence": "EXTRACTED", "source_file": "SECURITY_AUDIT_SCRIPT.sh", "source_location": "L43", "weight": 1.0}, {"source": "home_user_imobi_security_audit_script_sh", "target": "imobi_security_audit_script_check_env_var", "relation": "defines", "confidence": "EXTRACTED", "source_file": "SECURITY_AUDIT_SCRIPT.sh", "source_location": "L52", "weight": 1.0}, {"source": "home_user_imobi_security_audit_script_sh__entry", "target": "imobi_security_audit_script_check_env_var", "relation": "calls", "confidence": "EXTRACTED", "source_file": "SECURITY_AUDIT_SCRIPT.sh", "source_location": "L66", "weight": 1.0, "context": "call"}, {"source": "home_user_imobi_security_audit_script_sh__entry", "target": "imobi_security_audit_script_fail", "relation": "calls", "confidence": "EXTRACTED", "source_file": "SECURITY_AUDIT_SCRIPT.sh", "source_location": "L75", "weight": 1.0, "context": "call"}, {"source": "home_user_imobi_security_audit_script_sh__entry", "target": "imobi_security_audit_script_pass", "relation": "calls", "confidence": "EXTRACTED", "source_file": "SECURITY_AUDIT_SCRIPT.sh", "source_location": "L77", "weight": 1.0, "context": "call"}, {"source": "home_user_imobi_security_audit_script_sh__entry", "target": "imobi_security_audit_script_warn", "relation": "calls", "confidence": "EXTRACTED", "source_file": "SECURITY_AUDIT_SCRIPT.sh", "source_location": "L102", "weight": 1.0, "context": "call"}, {"source": "imobi_security_audit_script_check_env_var", "target": "imobi_security_audit_script_fail", "relation": "calls", "confidence": "EXTRACTED", "source_file": "SECURITY_AUDIT_SCRIPT.sh", "source_location": "L54", "weight": 1.0, "context": "call"}, {"source": "imobi_security_audit_script_check_env_var", "target": "imobi_security_audit_script_pass", "relation": "calls", "confidence": "EXTRACTED", "source_file": "SECURITY_AUDIT_SCRIPT.sh", "source_location": "L62", "weight": 1.0, "context": "call"}]}